{
  "schema_version": 1,
  "plugins": [
    {
      "id": "api",
      "name": "Public API Plugin",
      "description": "Public, API-key-authenticated HTTP surface for Peckboard, served as a WASM plugin. Lets external clients list projects, list/create cards, and manage scoped API keys over a /plugin-api/* prefix.",
      "author": "PeckBoard",
      "homepage": "https://github.com/PeckBoard/api-plugin",
      "version": "0.2.2",
      "hooks": [
        "http.request.before"
      ],
      "url": "https://github.com/PeckBoard/api-plugin/releases/download/v0.2.2/api.wasm",
      "sha256": "d0fa23aac56a05dc11aef3421927a24b7fa14419076cfc7e8903bc2c9cf0184d",
      "min_peckboard": "0.0.19"
    },
    {
      "id": "diff-viewer",
      "name": "Diff Viewer",
      "description": "Pick any git repo in the project/session folder, then get a side-by-side viewer/editor for every file that differs from origin/main, including new files and images, served as a WASM plugin.",
      "author": "PeckBoard",
      "homepage": "https://github.com/PeckBoard/diff-viewer",
      "version": "0.3.1",
      "hooks": [
        "http.request.before",
        "http.request.authed"
      ],
      "url": "https://github.com/PeckBoard/diff-viewer/releases/download/v0.3.1/diff-viewer.wasm",
      "sha256": "66ae8b127d9a4d254da4b47a2ef21a6a863316fb468412f14ceedf8f14e830bd",
      "min_peckboard": "0.0.28"
    },
    {
      "id": "experts",
      "name": "Experts",
      "description": "Experts feature for Peckboard (knowledge / question / PM experts, MCP tools, and UI), served as a WASM plugin.",
      "author": "PeckBoard",
      "homepage": "https://github.com/PeckBoard/experts",
      "version": "0.2.1",
      "hooks": [
        "mcp.tool.invoke",
        "http.request.before",
        "http.request.authed",
        "session.user.answer"
      ],
      "url": "https://github.com/PeckBoard/experts/releases/download/v0.2.1/experts.wasm",
      "sha256": "4f251f3503d7f6560df8a070c3c8c90af7a97081804f66458015f4a61444def6",
      "min_peckboard": "0.0.19"
    },
    {
      "id": "session-control",
      "name": "Session Control",
      "description": "Control another Peckboard session from a session: interrupt, terminate the agent, clear, and send messages/images. Served as a WASM plugin.",
      "author": "PeckBoard",
      "homepage": "https://github.com/PeckBoard/session-control",
      "version": "0.1.0",
      "hooks": [
        "mcp.tool.invoke"
      ],
      "url": "https://github.com/PeckBoard/session-control/releases/download/v0.1.0/session-control.wasm",
      "sha256": "02640fe2a387b4af07fdcfd23a1841167eb1bb8a661b145fcc029db067c753b7",
      "min_peckboard": "0.0.19"
    },
    {
      "id": "playwright-video",
      "name": "Playwright Tests",
      "description": "LogRocket-style replay of recorded browser test runs (per-step frames, time-scaled playback, action event track), with a Playwright Tests page below Sessions.",
      "author": "PeckBoard",
      "homepage": "https://github.com/PeckBoard/playwright-video",
      "version": "0.1.0",
      "hooks": [
        "http.request.before",
        "http.request.authed"
      ],
      "url": "https://github.com/PeckBoard/playwright-video/releases/download/v0.1.0/playwright-video.wasm",
      "sha256": "5f4b42e63bf3969b6f75b5894b8b85a41382167675f92f92174cb77234ff557a",
      "min_peckboard": "0.0.52"
    }
  ]
}
